{
  "gitSyncId": "66da1e760df75511e6fe16f6_95dcc7ff-6107-4bbd-a4d1-73dd4092fc66",
  "id": "Dashboard2_Select_public_customers1",
  "pluginId": "postgres-plugin",
  "pluginType": "DB",
  "unpublishedAction": {
    "actionConfiguration": {
      "body": "SELECT\n  *\nFROM\n  public.customers\nORDER BY\n  \"{{tbl_customers.sortOrder.column || 'customer_id'}}\" {{tbl_customers.sortOrder.order !== \"desc\" ? \"\" : \"DESC\"}}\nLIMIT\n  {{tbl_customers.pageSize}}\nOFFSET\n  {{tbl_customers.pageOffset}}",
      "encodeParamsToggle": true,
      "paginationType": "NONE",
      "pluginSpecifiedTemplates": [
        {
          "value": false
        }
      ],
      "timeoutInMillisecond": 10000
    },
    "confirmBeforeExecute": false,
    "datasource": {
      "id": "Untitled datasource 1",
      "isAutoGenerated": false,
      "name": "Untitled datasource 1",
      "pluginId": "postgres-plugin"
    },
    "dynamicBindingPathList": [
      {
        "key": "body"
      }
    ],
    "executeOnLoad": true,
    "name": "Select_public_customers1",
    "pageId": "Dashboard2",
    "userSetOnLoad": false
  }
}