{
  "gitSyncId": "66da1e760df75511e6fe16f6_0034cc84-0b84-4e45-8078-783b19c4b7c2",
  "id": "Authentication2_functions.register",
  "pluginId": "js-plugin",
  "pluginType": "JS",
  "unpublishedAction": {
    "actionConfiguration": {
      "encodeParamsToggle": true,
      "jsArguments": [],
      "paginationType": "NONE",
      "timeoutInMillisecond": 10000
    },
    "collectionId": "Authentication2_functions",
    "confirmBeforeExecute": false,
    "datasource": {
      "isAutoGenerated": false,
      "name": "UNUSED_DATASOURCE",
      "pluginId": "js-plugin"
    },
    "dynamicBindingPathList": [
      {
        "key": "body"
      }
    ],
    "executeOnLoad": false,
    "fullyQualifiedName": "functions.register",
    "name": "register",
    "pageId": "Authentication2",
    "userSetOnLoad": false
  }
}